{"P8": {"labels": ["docker"], "postTitle": "docker\u5b89\u88c5mysql5.7", "postUrl": "post/docker-an-zhuang-mysql5.7.html", "createdDate": "2024-06-20", "dateLabelColor": "#bc4c00"}, "P7": {"labels": ["docker"], "postTitle": "docker\u5b89\u88c5sqlserver2019", "postUrl": "post/docker-an-zhuang-sqlserver2019.html", "createdDate": "2024-06-20", "dateLabelColor": "#bc4c00"}, "P6": {"labels": ["docker"], "postTitle": "docker\u5b89\u88c5portainer-ce", "postUrl": "post/docker-an-zhuang-portainer-ce.html", "createdDate": "2024-06-20", "dateLabelColor": "#bc4c00"}, "P5": {"labels": ["docker"], "postTitle": "docker\u5b89\u88c5jenkins", "postUrl": "post/docker-an-zhuang-jenkins.html", "createdDate": "2024-06-20", "dateLabelColor": "#bc4c00"}, "P4": {"labels": ["docker"], "postTitle": "Centos\u5b89\u88c5docker", "postUrl": "post/Centos-an-zhuang-docker.html", "createdDate": "2024-06-20", "dateLabelColor": "#bc4c00"}, "labelColorDict": {"bug": "#d73a4a", "docker": "#B60205", "documentation": "#0075ca", "duplicate": "#cfd3d7", "enhancement": "#a2eeef", "good first issue": "#7057ff", "help wanted": "#008672", "invalid": "#e4e669", "question": "#d876e3", "wontfix": "#ffffff"}}